date_filling/__init__.py
date_filling/filling.py
date_filling-1.0.1.dist-info/LICENSE
date_filling-1.0.1.dist-info/METADATA
date_filling-1.0.1.dist-info/WHEEL
date_filling-1.0.1.dist-info/top_level.txt
date_filling-1.0.1.dist-info/RECORD
