Metadata-Version: 2.1
Name: date_filling
Version: 1.0.1
Summary: Just for fun
Author-email: Dilanka Rathnasiri <rdilanka17@gmail.com>
Maintainer-email: Dilanka Rathnasiri <rdilanka17@gmail.com>
License: MIT License
Requires-Python: >=3.8
License-File: LICENSE
Requires-Dist: numpy
